{
    "configurations": [
        {
            "name": "STM32",
            "includePath": [
                "Core/Inc",
                "Drivers/CMSIS/Device/ST/STM32F4xx/Include",
                "Drivers/CMSIS/Include",
                "Drivers/STM32F4xx_HAL_Driver/Inc",
                "Drivers/STM32F4xx_HAL_Driver/Inc/Legacy",
                "${workspaceFolder}/USB_DEVICE/App",
                "${workspaceFolder}/Project/Inc",
                "${workspaceFolder}/Middlewares/ST/STM32_USB_Device_Library/Core/Inc",
                "${workspaceFolder}/USB_DEVICE/Target",
                "${workspaceFolder}/Middlewares/ST/STM32_USB_Device_Library/Class/CDC/Inc",
                "${workspaceFolder}/Project/Inc/HMC5883L",
                "${workspaceFolder}/Project/Inc/MPU6050",
                "${workspaceFolder}/Project/Inc/ADXL345",
                "${workspaceFolder}/Project/Inc/BMP085",
                "${workspaceFolder}/Project/Inc/VL53L5CX",
                "${workspaceFolder}/Project/Inc/QMC5883L",
                "${workspaceFolder}/Project/Inc/MPU9250",
                "${workspaceFolder}/Project/Inc/AK8963"
            ],
            "defines": [
                "STM32F411xE",
                "USE_FULL_LL_DRIVER",
                "USE_HAL_DRIVER"
            ],
            "compilerPath": "/usr/bin/arm-none-eabi-g++"
        }
    ],
    "version": 4
}